cwv_scanner/__init__.py
cwv_scanner/cwv_scanner.py
cwv_scanner/user_agents.json
cwv_scanner/vulnerabilities.json
cwv_scanner/waf_indicators.json
cwv_scanner/banners/banner1.txt
cwv_scanner/banners/banner2.txt
cwv_scanner-1.0.2.dist-info/licenses/LICENSE
cwv_scanner-1.0.2.dist-info/METADATA
cwv_scanner-1.0.2.dist-info/WHEEL
cwv_scanner-1.0.2.dist-info/entry_points.txt
cwv_scanner-1.0.2.dist-info/top_level.txt
cwv_scanner-1.0.2.dist-info/RECORD
