Metadata-Version: 2.4
Name: cwv-scanner
Version: 1.0.2
Summary: Common Web Application Vulnerability Scanner
Home-page: https://github.com/sircryptic/cwv-scanner
Author: SirCryptic
Classifier: Programming Language :: Python :: 3
Classifier: License :: OSI Approved :: MIT License
Classifier: Operating System :: OS Independent
Requires-Python: >=3.11
License-File: LICENSE
Requires-Dist: requests
Requires-Dist: fake-useragent
Requires-Dist: tabulate
Requires-Dist: beautifulsoup4
Dynamic: author
Dynamic: classifier
Dynamic: description
Dynamic: description-content-type
Dynamic: home-page
Dynamic: license-file
Dynamic: requires-dist
Dynamic: requires-python
Dynamic: summary
